morten/__init__.py
morten/py.typed
morten-0.1.0.dist-info/METADATA
morten-0.1.0.dist-info/WHEEL
morten-0.1.0.dist-info/RECORD
